ndexutil/__init__.py
ndexutil/argparseutil.py
ndexutil/config.py
ndexutil/cytoscape.py
ndexutil/exceptions.py
ndexutil/ndex.py
ndexutil/ndexmisctools.py
ndexutil/networkx.py
ndexutil/reports.py
ndexutil/tutorial_utils.py
ndexutil/ebs/__init__.py
ndexutil/ebs/ebs2cx.py
ndexutil/tsv/__init__.py
ndexutil/tsv/cx2ndex.py
ndexutil/tsv/loaderutils.py
ndexutil/tsv/loading_plan_schema.json
ndexutil/tsv/streamtsvloader.py
ndexutil/tsv/tsv2nicecx2.py
ndexutil-0.14.0.data/data/schema/loading_plan_schema.json
ndexutil-0.14.0.data/scripts/ndexmisctools.py
tests/__init__.py
tests/test_cytoscapelayoutcommand.py
tests/test_ndex.py
tests/test_ndexmisctoolstsvloader.py
tests/test_networkxlayoutcommand.py
tests/test_networkxlayoutwrapper.py
tests/test_nodeattributeadder.py
tests/test_nodeattributeremover.py
tests/test_styleupdator.py
tests/tsv/__init__.py
tests/tsv/test_genesymbolsearcher.py
tests/tsv/test_networkissuereport.py
tests/tsv/test_streamtsvloader.py
tests/tsv/test_tsv2nicecx2.py
ndexutil-0.14.0.dist-info/METADATA
ndexutil-0.14.0.dist-info/WHEEL
ndexutil-0.14.0.dist-info/top_level.txt
ndexutil-0.14.0.dist-info/RECORD
