Metadata-Version: 2.1
Name: ndexutil
Version: 0.14.0
Summary: Unsupported NDEx utilities
Home-page: https://github.com/ndexbio/ndexutils
Author: The NDEx Project
Author-email: contact@ndexbio.org
License: BSD
Keywords: network analysis biology
Platform: UNKNOWN
Classifier: Development Status :: 3 - Alpha
Classifier: Natural Language :: English
Classifier: Intended Audience :: Science/Research
Classifier: Topic :: Scientific/Engineering :: Information Analysis
Classifier: Topic :: Scientific/Engineering :: Bio-Informatics
Classifier: Topic :: Scientific/Engineering :: Medical Science Apps.
Classifier: License :: OSI Approved :: BSD License
Classifier: Programming Language :: Python :: 3.4
Classifier: Programming Language :: Python :: 3.5
Classifier: Programming Language :: Python :: 3.6
Classifier: Programming Language :: Python :: 3.7
Requires-Dist: ndex2 (<4.0.0,>=3.3.0)
Requires-Dist: requests
Requires-Dist: requests-toolbelt
Requires-Dist: networkx
Requires-Dist: urllib3 (>=1.16)
Requires-Dist: pandas
Requires-Dist: mygene
Requires-Dist: jsonschema
Requires-Dist: biothings-client
Requires-Dist: ijson
Requires-Dist: tqdm
